QueriPlug/__init__.py
QueriPlug/connections.py
QueriPlug-1.0.5.dist-info/LICENSE
QueriPlug-1.0.5.dist-info/METADATA
QueriPlug-1.0.5.dist-info/WHEEL
QueriPlug-1.0.5.dist-info/top_level.txt
QueriPlug-1.0.5.dist-info/RECORD
