Metadata-Version: 2.1
Name: QueriPlug
Version: 1.0.5
Summary: A SQLite3 wrapper for python
Author: Ivan Zabrodin
Project-URL: Homepage, https://github.com/IvanVZabrodin/QueriPlug
Classifier: Programming Language :: Python :: 3
Classifier: License :: OSI Approved :: GNU General Public License v2 (GPLv2)
Classifier: Operating System :: OS Independent
Requires-Python: >=3.7
License-File: LICENSE
